bendlog/__init__.py
bendlog/readers.py
bendlog-0.1.0.dist-info/METADATA
bendlog-0.1.0.dist-info/WHEEL
bendlog-0.1.0.dist-info/top_level.txt
bendlog-0.1.0.dist-info/RECORD
