Metadata-Version: 2.4
Name: bendlog
Version: 0.1.0
Summary: Utilities for analyzing Databend logs
Project-URL: Homepage, https://github.com/datafuselabs/databend
Classifier: Programming Language :: Python :: 3
Classifier: License :: OSI Approved :: MIT License
Classifier: Operating System :: OS Independent
Requires-Python: >=3.10
Requires-Dist: zstandard>=0.20.0
Provides-Extra: dev
Requires-Dist: pytest>=7.0; extra == "dev"
Provides-Extra: publish
Requires-Dist: build; extra == "publish"
Requires-Dist: twine; extra == "publish"
